[{"sentence": "\"The lake is a long way from here.\""}, {"sentence": "\"Malls are great places to shop; I can find everything I need under one roof.\""}, {"sentence": "\"A purple pig and a green donkey flew a kite in the middle of the night and ended up sunburnt.\""}, {"sentence": "\"Let me help you with your baggage.\""}, {"sentence": "\"She did not cheat on the test, for it was not the right thing to do.\""}, {"sentence": "\"A song can make or ruin a person\u2019s day if they let it get to them.\""}, {"sentence": "\"The quick brown fox jumps over the lazy dog.\""}, {"sentence": "\"I am counting my calories, yet I really want dessert.\""}, {"sentence": "\"She works two jobs to make ends meet; at least, that was her reason for not having time to join us.\""}, {"sentence": "\"He decided to live out the rest of his life in solitude.\""}]